{
  "title": "306: No Such Thing As Heavy Snuggle-Pupping",
  "link": "https://www.patreon.com/posts/306-no-such-as-69603765",
  "pubDate": "Tue, 26 Jul 2022 16:10:31 GMT",
  "content": "<p><img data-media-id=\"162004793\"></p><p>Dan, James, Anna and John Lloyd discuss correct gambling attire, the inventor of Vaseline, and Athens' sixteen thousand secret swimming pools.</p>",
  "contentSnippet": "Dan, James, Anna and John Lloyd discuss correct gambling attire, the inventor of Vaseline, and Athens' sixteen thousand secret swimming pools.",
  "guid": "69603765",
  "isoDate": "2022-07-26T16:10:31.000Z",
  "id": "69603765",
  "publishDate": "2022-07-26T16:10:31.000Z",
  "dirName": "2022-07-26_306-no-such-thing-as-heavy-snuggle-pupping",
  "processedAt": "2025-09-30T01:51:48.975Z"
}