{
  "title": "138: No Such Thing As Fluff Island",
  "link": "https://www.patreon.com/posts/138-no-such-as-69591238",
  "pubDate": "Tue, 26 Jul 2022 10:14:47 GMT",
  "enclosure": {
    "url": "https://c10.patreonusercontent.com/4/patreon-media/p/post/69591238/9581937f229d43a8b0fd375dcb94e6b8/eyJhIjoxLCJpc19hdWRpbyI6MSwicCI6MX0%3D/1.mp3?token-hash=TwG770osxlmk7gLMZLiP-X3pihSAPaeraxSEL9a4MqI%3D&token-time=1759795200",
    "length": "35641088",
    "type": "audio/mpeg"
  },
  "content": "<p><img data-media-id=\"161970612\"></p><p>Andy, Anna, Alex and special guest Ed Brooke-Hitching discuss left-handed snails, non-existent islands and the White House press-pit-swimming-pool.</p>",
  "contentSnippet": "Andy, Anna, Alex and special guest Ed Brooke-Hitching discuss left-handed snails, non-existent islands and the White House press-pit-swimming-pool.",
  "guid": "69591238",
  "isoDate": "2022-07-26T10:14:47.000Z",
  "itunes": {
    "image": "https://c10.patreonusercontent.com/4/patreon-media/p/campaign/8889821/f44225ce10af4554843296a7d2c897fa/eyJkIjo3MiwiaCI6MzAwMCwic3RyaXBfYWxwaGEiOjEsInciOjMwMDAsIndlYnAiOjB9/2.png?token-hash=IynCE2n6JN_RAFsQp7WuuQ8iNNNSkLd6Q6F1OzrYkms%3D"
  },
  "id": "69591238",
  "publishDate": "2022-07-26T10:14:47.000Z",
  "dirName": "2022-07-26_138-no-such-thing-as-fluff-island",
  "bootstrappedAt": "2025-09-29T18:00:08.541Z"
}