{
  "title": "Little Fish: See You In The Charts",
  "link": "https://www.patreon.com/posts/little-fish-see-151156618",
  "pubDate": "Mon, 23 Feb 2026 00:01:00 GMT",
  "content": "<html><p>Dan, James and Andy discuss YOUR facts, including baseball, bridges and Ryan Bingham. We also learn why you don't want a meeting with Andy, no matter how handsome he might be. And we bestow eight facts on Friends of the Podcast. </p></html>",
  "contentSnippet": "Dan, James and Andy discuss YOUR facts, including baseball, bridges and Ryan Bingham. We also learn why you don't want a meeting with Andy, no matter how handsome he might be. And we bestow eight facts on Friends of the Podcast.",
  "guid": "151156618",
  "isoDate": "2026-02-23T00:01:00.000Z",
  "id": "151156618",
  "publishDate": "2026-02-23T00:01:00.000Z",
  "dirName": "2026-02-23_little-fish-see-you-in-the-charts",
  "itunes": {
    "duration": "1758",
    "episode": "17",
    "season": "2",
    "episodeType": "bonus"
  },
  "processedAt": "2026-02-27T05:03:30.141Z"
}