{
  "title": "Bonus: Drop Us A Line - Do Bears Like Listening To Fish?",
  "link": "https://www.patreon.com/posts/bonus-drop-us-do-147575196",
  "pubDate": "Wed, 07 Jan 2026 00:02:03 GMT",
  "content": "<html><p>Dan, James and Andy sift through the correspondence sent in by listeners.</p><p>Visit <a href=\"https://nosuchthingasafish.com\" target=\"_blank\">nosuchthingasafish.com</a> for news about live shows, merchandise and more episodes.</p><p>If you'd like to write in, you can email <a href=\"mailto:podcast@qi.com\" target=\"_blank\">podcast@qi.com</a></p></html>",
  "contentSnippet": "Dan, James and Andy sift through the correspondence sent in by listeners.\nVisit nosuchthingasafish.com for news about live shows, merchandise and more episodes.\nIf you'd like to write in, you can email podcast@qi.com",
  "guid": "147575196",
  "isoDate": "2026-01-07T00:02:03.000Z",
  "id": "147575196",
  "publishDate": "2026-01-07T00:02:03.000Z",
  "dirName": "2026-01-07_bonus-drop-us-a-line-do-bears-like-listening-to-fish",
  "itunes": {
    "duration": "1717",
    "episodeType": "bonus"
  },
  "processedAt": "2026-01-09T05:03:29.460Z"
}