{
  "title": "Bonus - Fish Breakfast Club - Episode 2",
  "link": "https://www.patreon.com/posts/bonus-fish-club-117450480",
  "pubDate": "Tue, 10 Dec 2024 00:01:00 GMT",
  "content": "<p>Enjoy breakfast No Such Thing As A Fish style, with this series of chats recorded during our tour of Australia and New Zealand.</p><p>Expect newly-learned facts, behind-the-scenes stories, omelettes, coffee, and omelettes.</p>",
  "contentSnippet": "Enjoy breakfast No Such Thing As A Fish style, with this series of chats recorded during our tour of Australia and New Zealand.\nExpect newly-learned facts, behind-the-scenes stories, omelettes, coffee, and omelettes.",
  "guid": "117450480",
  "isoDate": "2024-12-10T00:01:00.000Z",
  "id": "117450480",
  "publishDate": "2024-12-10T00:01:00.000Z",
  "dirName": "2024-12-10_bonus-fish-breakfast-club-episode-2",
  "itunes": {
    "episodeType": "bonus"
  },
  "bootstrappedAt": "2025-09-29T18:10:47.290Z"
}