{
  "title": "334: No Such Thing As A Babysitter's Trade Union",
  "link": "https://www.patreon.com/posts/334-no-such-as-69607109",
  "pubDate": "Tue, 26 Jul 2022 17:25:58 GMT",
  "content": "<p><img data-media-id=\"162014324\"></p><p>Dan, James, Anna and Andy discuss swimming, wrestling, necking, and a very unfortunate giraffe.</p>",
  "contentSnippet": "Dan, James, Anna and Andy discuss swimming, wrestling, necking, and a very unfortunate giraffe.",
  "guid": "69607109",
  "isoDate": "2022-07-26T17:25:58.000Z",
  "id": "69607109",
  "publishDate": "2022-07-26T17:25:58.000Z",
  "dirName": "2022-07-26_334-no-such-thing-as-a-babysitter-s-trade-union",
  "processedAt": "2025-09-30T01:51:48.857Z"
}